finazon_grpc_python_client/__init__.py
finazon_grpc_python_client/api_usage_pb2.py
finazon_grpc_python_client/api_usage_pb2.pyi
finazon_grpc_python_client/api_usage_pb2_grpc.py
finazon_grpc_python_client/benzinga_pb2.py
finazon_grpc_python_client/benzinga_pb2.pyi
finazon_grpc_python_client/benzinga_pb2_grpc.py
finazon_grpc_python_client/binance_pb2.py
finazon_grpc_python_client/binance_pb2.pyi
finazon_grpc_python_client/binance_pb2_grpc.py
finazon_grpc_python_client/datasets_pb2.py
finazon_grpc_python_client/datasets_pb2.pyi
finazon_grpc_python_client/datasets_pb2_grpc.py
finazon_grpc_python_client/exchange_pb2.py
finazon_grpc_python_client/exchange_pb2.pyi
finazon_grpc_python_client/exchange_pb2_grpc.py
finazon_grpc_python_client/publishers_pb2.py
finazon_grpc_python_client/publishers_pb2.pyi
finazon_grpc_python_client/publishers_pb2_grpc.py
finazon_grpc_python_client/sec_pb2.py
finazon_grpc_python_client/sec_pb2.pyi
finazon_grpc_python_client/sec_pb2_grpc.py
finazon_grpc_python_client/sip_pb2.py
finazon_grpc_python_client/sip_pb2.pyi
finazon_grpc_python_client/sip_pb2_grpc.py
finazon_grpc_python_client/snapshot_pb2.py
finazon_grpc_python_client/snapshot_pb2.pyi
finazon_grpc_python_client/snapshot_pb2_grpc.py
finazon_grpc_python_client/tickers_pb2.py
finazon_grpc_python_client/tickers_pb2.pyi
finazon_grpc_python_client/tickers_pb2_grpc.py
finazon_grpc_python_client/time_series_pb2.py
finazon_grpc_python_client/time_series_pb2.pyi
finazon_grpc_python_client/time_series_pb2_grpc.py
finazon_grpc_python_client/trade_pb2.py
finazon_grpc_python_client/trade_pb2.pyi
finazon_grpc_python_client/trade_pb2_grpc.py
requirements.txt
sga_finazon_grpc_python_client-1.0.5.dist-info/LICENSE
sga_finazon_grpc_python_client-1.0.5.dist-info/METADATA
sga_finazon_grpc_python_client-1.0.5.dist-info/WHEEL
sga_finazon_grpc_python_client-1.0.5.dist-info/RECORD
