Metadata-Version: 2.1
Name: sga-finazon-grpc-python-client
Version: 1.0.5
Summary: Finazon gRPC client library for Python
Home-page: https://github.com/mivxxx/finazon-grpc-python-client
License: MIT
Author: Finazon
Author-email: team@finazon.io
Requires-Python: >=3.8,<4.0
Classifier: License :: OSI Approved :: MIT License
Classifier: Programming Language :: Python :: 3
Classifier: Programming Language :: Python :: 3.8
Classifier: Programming Language :: Python :: 3.9
Classifier: Programming Language :: Python :: 3.10
Classifier: Programming Language :: Python :: 3.11
Requires-Dist: grpcio (==1.58.0)
Requires-Dist: grpcio-tools (==1.58.0)
Requires-Dist: mypy-protobuf (>=3.5.0,<4.0.0)
Project-URL: Repository, https://github.com/mivxxx/finazon-grpc-python-client
